rotorpy/__init__.py
rotorpy/environments.py
rotorpy/simulate.py
rotorpy/world.py
rotorpy/controllers/__init__.py
rotorpy/controllers/controller_template.py
rotorpy/controllers/quadrotor_control.py
rotorpy/estimators/__init__.py
rotorpy/estimators/nullestimator.py
rotorpy/estimators/wind_ekf.py
rotorpy/estimators/wind_ukf.py
rotorpy/learning/__init__.py
rotorpy/learning/learning_utils.py
rotorpy/learning/quadrotor_environments.py
rotorpy/learning/quadrotor_reward_functions.py
rotorpy/sensors/__init__.py
rotorpy/sensors/external_mocap.py
rotorpy/sensors/imu.py
rotorpy/sensors/range_sensors.py
rotorpy/trajectories/__init__.py
rotorpy/trajectories/batched_traj.py
rotorpy/trajectories/circular_traj.py
rotorpy/trajectories/hover_traj.py
rotorpy/trajectories/lissajous_traj.py
rotorpy/trajectories/minsnap.py
rotorpy/trajectories/speed_traj.py
rotorpy/trajectories/traj_template.py
rotorpy/utils/__init__.py
rotorpy/utils/animate.py
rotorpy/utils/attitude_gain_sysidtool.py
rotorpy/utils/numpy_encoding.py
rotorpy/utils/occupancy_map.py
rotorpy/utils/plotter.py
rotorpy/utils/postprocessing.py
rotorpy/utils/shapes.py
rotorpy/utils/system_info.py
rotorpy/utils/trajgen_utils.py
rotorpy/vehicles/__init__.py
rotorpy/vehicles/ardupilot_multirotor.py
rotorpy/vehicles/crazyflie_params.py
rotorpy/vehicles/crazyfliebrushless_params.py
rotorpy/vehicles/hummingbird_params.py
rotorpy/vehicles/multirotor.py
rotorpy/vehicles/px4_multirotor.py
rotorpy/vehicles/px4_sihsim_quadx_params.py
rotorpy/wind/__init__.py
rotorpy/wind/batched_wind.py
rotorpy/wind/default_winds.py
rotorpy/wind/dryden_utils.py
rotorpy/wind/dryden_winds.py
rotorpy/wind/spatial_winds.py
rotorpy/wind/wind_template.py
rotorpy/worlds/__init__.py
rotorpy-2.1.0.dist-info/licenses/LICENSE.md
rotorpy-2.1.0.dist-info/METADATA
rotorpy-2.1.0.dist-info/WHEEL
rotorpy-2.1.0.dist-info/top_level.txt
rotorpy-2.1.0.dist-info/RECORD
