Metadata-Version: 2.4
Name: rotorpy
Version: 2.1.0
Summary: A multirotor simulator with aerodynamics for education and research.
Author-email: Spencer Folk <spencer.folk@gmail.com>
Maintainer-email: Spencer Folk <spencer.folk@gmail.com>
License: Copyright 2023 RotorPy Authors
Project-URL: Homepage, https://github.com/spencerfolk/rotorpy
Project-URL: Bug Reports, https://github.com/spencerfolk/rotorpy/issues
Project-URL: Source, https://github.com/spencerfolk/rotorpy
Keywords: drone,uav,quadrotor,multirotor,aerodynamics,simulation,controls,robotics,estimation
Classifier: Development Status :: 4 - Beta
Classifier: Intended Audience :: Developers
Classifier: License :: OSI Approved :: MIT License
Classifier: Operating System :: OS Independent
Classifier: Programming Language :: Python :: 3
Classifier: Programming Language :: Python :: 3 :: Only
Requires-Python: >=3.8
License-File: LICENSE.md
Requires-Dist: pyyaml
Requires-Dist: cvxopt
Requires-Dist: matplotlib
Requires-Dist: numpy>=1.24
Requires-Dist: scipy
Requires-Dist: pandas
Requires-Dist: tqdm
Requires-Dist: gymnasium
Requires-Dist: roma
Requires-Dist: torch>=1.11.0
Requires-Dist: torchdiffeq
Requires-Dist: opt-einsum
Requires-Dist: timed_count
Provides-Extra: learning
Requires-Dist: stable_baselines3; extra == "learning"
Requires-Dist: tensorboard; extra == "learning"
Provides-Extra: dev
Requires-Dist: pytest; extra == "dev"
Requires-Dist: filterpy==1.4.5; extra == "dev"
Provides-Extra: testing
Requires-Dist: pytest; extra == "testing"
Requires-Dist: filterpy==1.4.5; extra == "testing"
Requires-Dist: stable_baselines3; extra == "testing"
Requires-Dist: pymavlink; extra == "testing"
Provides-Extra: filter
Requires-Dist: filterpy==1.4.5; extra == "filter"
Provides-Extra: px4
Requires-Dist: pymavlink; extra == "px4"
Provides-Extra: all
Requires-Dist: stable_baselines3; extra == "all"
Requires-Dist: tensorboard; extra == "all"
Requires-Dist: pytest; extra == "all"
Requires-Dist: filterpy==1.4.5; extra == "all"
Requires-Dist: pymavlink; extra == "all"
Dynamic: license-file
